mpyicbg/__init__.py
mpyicbg/errors.py
mpyicbg/transformations.py
mpyicbg/algorithms/__init__.py
mpyicbg/algorithms/ransac.py
mpyicbg/utils/__init__.py
mpyicbg/utils/numpy_utils.py
mpyicbg/utils/utils.py
mpyicbg-0.0.1.dist-info/METADATA
mpyicbg-0.0.1.dist-info/WHEEL
mpyicbg-0.0.1.dist-info/top_level.txt
mpyicbg-0.0.1.dist-info/RECORD
