Metadata-Version: 2.1
Name: mpyicbg
Version: 0.0.1
Summary: Python transformation library inspired by Stephan Saalfeld's MPICBG Java Library.
Home-page: https://github.com/RussTorres/m-py-icbg
Author: Russel Torres
Author-email: RussTorres@gmail.com
License: UNKNOWN
Platform: UNKNOWN
Requires-Dist: decorator
Requires-Dist: numpy
